{
  "resourceType": "SearchParameter",
  "id": "healthcareservice-name",
  "url": "http://hl7.org/fhir/us/directory-attestation/SearchParameter/healthcareservice-name",
  "version": "0.2.0",
  "name": "NatlDir_sp_healthcareservice_name",
  "status": "active",
  "date": "2022-09-21",
  "publisher": "HL7 Patient Administration Committee",
  "contact": [
    {
      "telecom": [
        {
          "system": "url",
          "value": "http://www.hl7.org/Special/committees/pafm/index.cfm"
        }
      ]
    }
  ],
  "description": "Select HealthcareServices with the specified name",
  "code": "name",
  "base": [
    "HealthcareService"
  ],
  "type": "string",
  "expression": "name",
  "multipleOr": true,
  "multipleAnd": true,
  "modifier": [
    "exact",
    "contains"
  ]
}